README
setup.cfg
setup.py
patternmatching/__init__.py
patternmatching/tests.py
py_pattern_matching.egg-info/PKG-INFO
py_pattern_matching.egg-info/SOURCES.txt
py_pattern_matching.egg-info/dependency_links.txt
py_pattern_matching.egg-info/top_level.txt