Metadata-Version: 1.0
Name: py-pattern-matching
Version: 0.1.1
Summary: Data-structure pattern matching and unpacking for Python
Home-page: https://github.com/eallik/py-pattern-matching
Author: Erik Allik
Author-email: eallik@gmail.com
License: UNKNOWN
Platform: UNKNOWN
